cam_distort-0.1.0.dist-info/METADATA
cam_distort-0.1.0.dist-info/WHEEL
cam_distort-0.1.0.dist-info/licenses/LICENSE
cam_distort/__init__.py
cam_distort/cam_distort.cpython-314-x86_64-linux-gnu.so
cam_distort-0.1.0.dist-info/RECORD
